sapit/__init__.py
sapit/main.py
sapit-1.5.dist-info/METADATA
sapit-1.5.dist-info/WHEEL
sapit-1.5.dist-info/entry_points.txt
sapit-1.5.dist-info/top_level.txt
sapit-1.5.dist-info/RECORD
