Metadata-Version: 2.1
Name: sapit
Version: 1.5
Summary: A Text-to-speech module
Author: Ali Lodhi
Author-email: alilodhibusiness@gmail.com
Requires-Dist: pyttsx3 ==2.90
Requires-Dist: pydub ==0.25.1
Requires-Dist: ffmpeg ==1.4
